mqt/qmap/__init__.py
mqt/qmap/_version.py
mqt/qmap/_version.pyi
mqt/qmap/clifford_synthesis.cpython-311-aarch64-linux-gnu.so
mqt/qmap/clifford_synthesis.pyi
mqt/qmap/hybrid_mapper.cpython-311-aarch64-linux-gnu.so
mqt/qmap/hybrid_mapper.pyi
mqt/qmap/py.typed
mqt/qmap/sc.cpython-311-aarch64-linux-gnu.so
mqt/qmap/sc.pyi
mqt/qmap/types.py
mqt/qmap/_compat/__init__.py
mqt/qmap/_compat/typing.py
mqt/qmap/libs/ibm_guadalupe_16.pickle
mqt/qmap/libs/rigetti_16.pickle
mqt/qmap/na/__init__.py
mqt/qmap/na/state_preparation.cpython-311-aarch64-linux-gnu.so
mqt/qmap/na/state_preparation.pyi
mqt/qmap/na/zoned.cpython-311-aarch64-linux-gnu.so
mqt/qmap/na/zoned.pyi
mqt/qmap/plugins/__init__.py
mqt/qmap/plugins/qiskit/__init__.py
mqt/qmap/plugins/qiskit/clifford_synthesis.py
mqt/qmap/plugins/qiskit/sc/__init__.py
mqt/qmap/plugins/qiskit/sc/compile.py
mqt/qmap/plugins/qiskit/sc/import_backend.py
mqt/qmap/plugins/qiskit/sc/load_architecture.py
mqt/qmap/plugins/qiskit/sc/load_calibration.py
mqt/qmap/plugins/qiskit/sc/subarchitectures.py
mqt/qmap/visualization/__init__.py
mqt/qmap/visualization/search_visualizer.py
mqt/qmap/visualization/visualize_search_graph.py
mqt_qmap.libs/libz3-341b2ed7.so.4.12
mqt_qmap-3.5.0.dist-info/METADATA
mqt_qmap-3.5.0.dist-info/WHEEL
mqt_qmap-3.5.0.dist-info/RECORD
mqt_qmap-3.5.0.dist-info/licenses/LICENSE.md
