Metadata-Version: 2.4
Name: mqt.qmap
Version: 3.5.0
Summary: A tool for Quantum Circuit Mapping
Keywords: MQT,quantum-computing,design-automation,compiler,clifford-synthesis
Author-Email: Lukas Burgholzer <lukas.burgholzer@tum.de>, Stefan Hillmich <stefan.hillmich@scch.at>, Tom Peham <tom.peham@tum.de>, Ludwig Schmid <ludwig.s.schmid@tum.de>, Yannick Stade <yannick.stade@tum.de>
License-Expression: MIT
License-File: LICENSE.md
Classifier: Topic :: Scientific/Engineering :: Electronic Design Automation (EDA)
Classifier: Intended Audience :: Science/Research
Classifier: Natural Language :: English
Classifier: Operating System :: POSIX :: Linux
Classifier: Operating System :: MacOS
Classifier: Operating System :: Microsoft :: Windows
Classifier: Programming Language :: C++
Classifier: Programming Language :: Python
Classifier: Programming Language :: Python :: 3
Classifier: Programming Language :: Python :: 3 :: Only
Classifier: Programming Language :: Python :: 3.10
Classifier: Programming Language :: Python :: 3.11
Classifier: Programming Language :: Python :: 3.12
Classifier: Programming Language :: Python :: 3.13
Classifier: Programming Language :: Python :: 3.14
Classifier: Development Status :: 5 - Production/Stable
Classifier: Typing :: Typed
Project-URL: Homepage, https://github.com/munich-quantum-toolkit/qmap
Project-URL: Documentation, https://mqt.readthedocs.io/projects/qmap
Project-URL: Issues, https://github.com/munich-quantum-toolkit/qmap/issues
Project-URL: Discussions, https://github.com/munich-quantum-toolkit/qmap/discussions
Requires-Python: !=3.14.1,>=3.10
Requires-Dist: mqt.core~=3.3.3
Requires-Dist: qiskit[qasm3-import]>=1.0.0
Requires-Dist: rustworkx[all]>=0.16.0
Requires-Dist: typing_extensions>=4.6; python_version < "3.11"
Provides-Extra: visualization
Requires-Dist: distinctipy>=1.3.4; extra == "visualization"
Requires-Dist: plotly>=6.0.1; extra == "visualization"
Requires-Dist: networkx>=3.2.1; extra == "visualization"
Requires-Dist: walkerlayout>=1.0.2; extra == "visualization"
Requires-Dist: ipywidgets>=8.1.7; extra == "visualization"
